pysofa2/__about__.py
pysofa2/__init__.py
pysofa2/_sofa_c.dylib
pysofa2/sofa.h
pysofa2/sofa_wrapper.py
pysofa2/sofam.h
pysofa2-23.10.11.2.dist-info/LICENSE
pysofa2-23.10.11.2.dist-info/METADATA
pysofa2-23.10.11.2.dist-info/WHEEL
pysofa2-23.10.11.2.dist-info/entry_points.txt
pysofa2-23.10.11.2.dist-info/RECORD
