Metadata-Version: 2.1
Name: pysofa2
Version: 23.10.11.2
Summary: A wrapper of the International Astronomical Union's SOFA lbrary.
Keywords: some,keywords
Author-email: Duncan Eddy <duncan.eddy@gmail.com>
Requires-Python: >=3.7
Classifier: Topic :: Scientific/Engineering :: Astronomy
Requires-Dist: numpy >=1.16.1,<2.0.0
Requires-Dist: pytest >=5.0.0,<6.0.0 ; extra == "dev"
Requires-Dist: pytest-cov >=2.7.1,<3.0.0 ; extra == "dev"
Requires-Dist: coveralls>=1.8.1,<2.0.0 ; extra == "dev"
Requires-Dist: travis-tox>=0.1.0,<1.0.0 ; extra == "dev"
Project-URL: Source, https://github.com/duncaneddy/pysofa2
Provides-Extra: dev
